.gitignore
README.txt
bootstrap.py
buildout.cfg
setup.py
docs/HISTORY.txt
src/ClueReleaseManager/__init__.py
src/ClueReleaseManager.paste.egg-info/PKG-INFO
src/ClueReleaseManager.paste.egg-info/SOURCES.txt
src/ClueReleaseManager.paste.egg-info/dependency_links.txt
src/ClueReleaseManager.paste.egg-info/entry_points.txt
src/ClueReleaseManager.paste.egg-info/namespace_packages.txt
src/ClueReleaseManager.paste.egg-info/not-zip-safe
src/ClueReleaseManager.paste.egg-info/requires.txt
src/ClueReleaseManager.paste.egg-info/top_level.txt
src/ClueReleaseManager/paste/__init__.py
src/ClueReleaseManager/paste/paste/__init__.py
src/ClueReleaseManager/paste/paste/docs/README.txt
src/ClueReleaseManager/paste/paste/doctests/README.txt
src/ClueReleaseManager/paste/paste/tests/__init__.py
src/ClueReleaseManager/paste/paste/tests/development.ini
src/ClueReleaseManager/paste/paste/tests/test_crm.py
src/ClueReleaseManager/paste/paste/tests/django/manage.py
src/ClueReleaseManager/paste/paste/tests/django/settings.py
src/ClueReleaseManager/paste/paste/tests/django/urls.py
src/ClueReleaseManager/paste/paste/tests/django/wrappers.py
src/ClueReleaseManager/paste/paste/tests/test_files/.empty