Metadata-Version: 1.0
Name: ClueReleaseManager.paste
Version: 1.1
Summary: Yet another WSGI Paste factory for paste and ClueReleaseManager sponsorised by Makina Corpus
Home-page: http://git.minitage.org/git/others/ClueReleaseManager.paste
Author: Mathieu Pasquet
Author-email: kiorky@cryptelium.net
License: BSD
Platform: UNKNOWN
Classifier: Programming Language :: Python
Classifier: Topic :: Software Development :: Libraries :: Python Modules
